README.md
setup.cfg
setup.py
padua/__init__.py
padua/analysis.py
padua/annotations.py
padua/filters.py
padua/imputation.py
padua/io.py
padua/normalization.py
padua/process.py
padua/utils.py
padua/visualize.py
padua.egg-info/PKG-INFO
padua.egg-info/SOURCES.txt
padua.egg-info/dependency_links.txt
padua.egg-info/requires.txt
padua.egg-info/top_level.txt